{
  "email": {
    "enabled": true,
    "smtp_host": "smtp.gmail.com",
    "smtp_port": 587,
    "smtp_user": "alerts@advanciapayledger.com",
    "smtp_password": "YOUR_APP_PASSWORD_HERE",
    "recipients": ["admin@advanciapayledger.com"],
    "from_name": "Advancia Watchdog"
  },
  "slack": {
    "enabled": false,
    "webhook_url": "https://hooks.slack.com/services/YOUR/WEBHOOK/URL",
    "channel": "#alerts",
    "username": "Advancia Status Bot",
    "icon_emoji": ":rotating_light:"
  },
  "discord": {
    "enabled": false,
    "webhook_url": "https://discord.com/api/webhooks/YOUR_WEBHOOK_ID/YOUR_TOKEN"
  },
  "pagerduty": {
    "enabled": false,
    "integration_key": "YOUR_PAGERDUTY_INTEGRATION_KEY"
  },
  "alert_thresholds": {
    "downtime_seconds": 30,
    "response_time_ms": 1000,
    "cpu_percent": 85,
    "memory_percent": 85,
    "disk_percent": 90,
    "ssl_expiry_days": 30
  },
  "quiet_hours": {
    "enabled": false,
    "start_hour": 22,
    "end_hour": 8,
    "timezone": "UTC"
  },
  "rate_limiting": {
    "enabled": true,
    "max_alerts_per_hour": 10,
    "cooldown_minutes": 15
  }
}
